scan_repo.py
autocommit/__init__.py
autocommit/commit.py
autocommit/llm.py
aicommit-0.1.0.dist-info/METADATA
aicommit-0.1.0.dist-info/WHEEL
aicommit-0.1.0.dist-info/entry_points.txt
aicommit-0.1.0.dist-info/licenses/LICENSE
aicommit-0.1.0.dist-info/RECORD
