Metadata-Version: 2.1
Name: aicommit
Version: 0.1.0
Summary: Generate AI powered commit messages
Project-URL: Homepage, https://github.com/abi/autocommit
Project-URL: Bug Tracker, https://github.com/abi/autocommit/issues
Author-email: Abi Raja <abimanyuraja@gmail.com>
License-File: LICENSE
Requires-Python: >=3.7
Requires-Dist: async-timeout~=4.0
Requires-Dist: black~=22.12.0
Requires-Dist: certifi~=2022.12.7
Requires-Dist: cffi~=1.15.1
Requires-Dist: charset-normalizer~=2.1.1
Requires-Dist: click~=8.1.3
Requires-Dist: et-xmlfile~=1.1.0
Requires-Dist: gitdb~=4.0.10
Requires-Dist: gitpython~=3.1.29
Requires-Dist: idna~=3.4
Requires-Dist: importlib-metadata~=5.2.0
Requires-Dist: jaraco-classes~=3.2.3
Requires-Dist: keyring~=23.13.1
Requires-Dist: langchain~=0.0.45
Requires-Dist: markdown~=3.4.1
Requires-Dist: more-itertools~=9.0.0
Requires-Dist: mypy-extensions~=0.4.3
Requires-Dist: numpy~=1.24.0
Requires-Dist: openai~=0.25.0
Requires-Dist: openpyxl~=3.0.10
Requires-Dist: pandas-stubs~=1.5.2.221213
Requires-Dist: pandas~=1.5.2
Requires-Dist: pathspec~=0.10.3
Requires-Dist: platformdirs~=2.6.0
Requires-Dist: prompt-toolkit~=1.0.14
Requires-Dist: pycparser~=2.21
Requires-Dist: pydantic~=1.10.2
Requires-Dist: pygit2~=1.11.1
Requires-Dist: pygments~=2.13.0
Requires-Dist: pyinquirer~=1.0.3
Requires-Dist: python-dateutil~=2.8.2
Requires-Dist: python-dotenv~=0.21.0
Requires-Dist: pytz~=2022.7
Requires-Dist: pyyaml~=6.0
Requires-Dist: redis~=4.4.0
Requires-Dist: regex~=2022.10.31
Requires-Dist: requests~=2.28.1
Requires-Dist: six~=1.16.0
Requires-Dist: smmap~=5.0.0
Requires-Dist: sqlalchemy~=1.4.45
Requires-Dist: tomli~=2.0.1
Requires-Dist: tqdm~=4.64.1
Requires-Dist: types-pytz~=2022.7.0.0
Requires-Dist: typing-extensions~=4.4.0
Requires-Dist: urllib3~=1.26.13
Requires-Dist: wcwidth~=0.2.5
Requires-Dist: zipp~=3.11.0
